autoft_orkut/__init__.py
autoft_orkut/client.cpython-312-x86_64-linux-gnu.so
autoft_orkut/device.cpython-312-x86_64-linux-gnu.so
autoft_orkut/qris.cpython-312-x86_64-linux-gnu.so
autoft_orkut/utils.cpython-312-x86_64-linux-gnu.so
autoft_orkut-0.0.2.dist-info/METADATA
autoft_orkut-0.0.2.dist-info/WHEEL
autoft_orkut-0.0.2.dist-info/top_level.txt
autoft_orkut-0.0.2.dist-info/RECORD
