Metadata-Version: 2.4
Name: autoft-orkut
Version: 0.0.2
Summary: Mutasi QRIS OrderKuota Client
Author: AutoFtBot69
License-Expression: MIT
Project-URL: Homepage, https://github.com/AutoFTbot/autoft-orkut
Requires-Python: >=3.7
Requires-Dist: requests>=2.25.0
Provides-Extra: imaging
Requires-Dist: qrcode[pil]>=7.0; extra == "imaging"
Requires-Dist: Pillow>=8.0; extra == "imaging"
